radiant/__init__.py
radiant/plot_compounds.py
radiant/tests/__init__.py
radiant/tests/test_plot_compounds.py
radiant_rdkit-0.2.0.dist-info/LICENSE
radiant_rdkit-0.2.0.dist-info/METADATA
radiant_rdkit-0.2.0.dist-info/WHEEL
radiant_rdkit-0.2.0.dist-info/top_level.txt
radiant_rdkit-0.2.0.dist-info/RECORD
