Metadata-Version: 2.1
Name: radiant-rdkit
Version: 0.2.0
Summary: short package to make publication quality rdkit plots
Home-page: https://codeberg.org/sail.black/acheeve.git
Author: Julian M. Kleber
Author-email: julian.kleber@sail.black
Classifier: Programming Language :: Python :: 3
Classifier: License :: OSI Approved :: GNU Affero General Public License v3 or later (AGPLv3+)
Classifier: Operating System :: OS Independent
Requires-Python: >=3.9
License-File: LICENSE
Requires-Dist: rdkit
Requires-Dist: cairosvg
